pytv/Converter.py
pytv/ModuleLoader.py
pytv/__init__.py
pytv/utils.py
verithon_test-0.2.dist-info/LICENSE
verithon_test-0.2.dist-info/METADATA
verithon_test-0.2.dist-info/WHEEL
verithon_test-0.2.dist-info/top_level.txt
verithon_test-0.2.dist-info/RECORD
